{
  "date": "2026-06-03",
  "responses": [
    {
      "date": "2026-06-03",
      "message": "",
      "submittedAt": "2026-06-03T10:49:58.533Z",
      "tasks": [
        {
          "progress": "100%",
          "taskId": "ou_ce056c51b867b816a10b42f6466bcd70-0",
          "timeSpent": "8h",
          "title": "North Carolina Museum Video 14 - ONLY 2.5 min in 4.5 min (2.5)"
        }
      ],
      "userId": "ou_ce056c51b867b816a10b42f6466bcd70"
    },
    {
      "date": "2026-06-03",
      "message": "Khum",
      "submittedAt": "2026-06-03T10:55:43.609Z",
      "tasks": [
        {
          "progress": "100%",
          "taskId": "ou_8bc85db08b634120548400c90c38d7c1-0",
          "timeSpent": "4h",
          "title": "SN Priority: 16. Left vs Right-Sided Heart Failure (NCLEX Must-Know) (2.5)"
        },
        {
          "progress": "20%",
          "taskId": "ou_8bc85db08b634120548400c90c38d7c1-1",
          "timeSpent": "3.5h",
          "title": "Flashcard: 8 cards (2) 172-175 + 229-232 + 12/6"
        }
      ],
      "userId": "ou_8bc85db08b634120548400c90c38d7c1"
    },
    {
      "userId": "ou_029556a9a2b266d13eead0db7af96c5b",
      "submittedAt": "2026-06-03T11:09:09.533Z",
      "date": "2026-06-03",
      "tasks": [
        {
          "taskId": "ou_029556a9a2b266d13eead0db7af96c5b-0",
          "title": "Flashcard: 8 cards (1.5)  211-218",
          "progress": "100%",
          "timeSpent": "2.5h"
        },
        {
          "taskId": "ou_029556a9a2b266d13eead0db7af96c5b-1",
          "title": "SN Priority: 14. Nursing Priorities for Diabetic Patients ~9min (2.5)",
          "progress": "40%",
          "timeSpent": "5.5h"
        }
      ],
      "message": ""
    }
  ]
}