{
  "date": "2026-05-27",
  "responses": [
    {
      "userId": "ou_029556a9a2b266d13eead0db7af96c5b",
      "submittedAt": "2026-05-27T10:47:07.628Z",
      "date": "2026-05-27",
      "tasks": [
        {
          "taskId": "ou_029556a9a2b266d13eead0db7af96c5b-0",
          "title": "Flashcard: 8 cards (1.5) 151-158",
          "progress": "100%",
          "timeSpent": "4h"
        },
        {
          "taskId": "ou_029556a9a2b266d13eead0db7af96c5b-1",
          "title": "Corporate training showreel (0.5)",
          "progress": "30%",
          "timeSpent": "4h"
        }
      ],
      "message": ""
    }
  ]
}